frontend/build/.DS_Store
frontend/build/asset-manifest.json
frontend/build/index.html
frontend/build/static/css/main.0a45b3dc.css
frontend/build/static/css/main.0a45b3dc.css.map
frontend/build/static/js/main.c6e9e899.js
frontend/build/static/js/main.c6e9e899.js.LICENSE.txt
frontend/build/static/js/main.c6e9e899.js.map
labeling/__init__.py
labeling/__main__.py
labeling/notebook/__init__.py
labeling/notebook/api_files.py
labeling/notebook/api_plugins.py
labeling/notebook/utils.py
labeling/plugin/__init__.py
labeling/plugin/example.py
labeling_notebook-0.6.1.dist-info/entry_points.txt
labeling_notebook-0.6.1.dist-info/LICENSE
labeling_notebook-0.6.1.dist-info/WHEEL
labeling_notebook-0.6.1.dist-info/METADATA
labeling_notebook-0.6.1.dist-info/RECORD
